bbae_invest_api/__init__.py
bbae_invest_api/bbae_api.py
bbae_invest_api-0.1.3.dist-info/LICENSE
bbae_invest_api-0.1.3.dist-info/METADATA
bbae_invest_api-0.1.3.dist-info/WHEEL
bbae_invest_api-0.1.3.dist-info/top_level.txt
bbae_invest_api-0.1.3.dist-info/RECORD
