Metadata-Version: 2.1
Name: bbae_invest_api
Version: 0.1.3
Summary: Unofficial BBAE Invest API written in Python Requests
Home-page: https://github.com/ImNotOssy/BBAE_investing_API
Author: Oswaldo Romero
License-File: LICENSE
Requires-Dist: pillow
Requires-Dist: python-dotenv
Requires-Dist: requests
